{
    "fujprog": {
        "branch": "master",
        "description": "FPGA ULX2/3 JTAG programmer",
        "homepage": "",
        "owner": "kost",
        "repo": "fujprog",
        "rev": "f498967a641e410931f5c8b5ba5c331e90bbef4b",
        "sha256": "05z9p3jmgjvhpkiyaxh1889032ww4n8g9xbi8yzgiqhmwknzxg9b",
        "type": "tarball",
        "url": "https://github.com/kost/fujprog/archive/f498967a641e410931f5c8b5ba5c331e90bbef4b.tar.gz",
        "url_template": "https://github.com/<owner>/<repo>/archive/<rev>.tar.gz"
    },
    "nextpnr": {
        "branch": "master",
        "description": "nextpnr portable FPGA place and route tool",
        "homepage": null,
        "owner": "YosysHQ",
        "repo": "nextpnr",
        "rev": "b5054f0d7777b7f831d2223479628372e968e89a",
        "sha256": "0jqgi59m1rshdwn7x1zjlwvx38gdhhkfajnbjdq6yd0vd74wn099",
        "type": "tarball",
        "url": "https://github.com/YosysHQ/nextpnr/archive/b5054f0d7777b7f831d2223479628372e968e89a.tar.gz",
        "url_template": "https://github.com/<owner>/<repo>/archive/<rev>.tar.gz"
    },
    "nixpkgs": {
        "branch": "release-20.09",
        "description": "Nix Packages collection",
        "homepage": "",
        "owner": "NixOS",
        "repo": "nixpkgs",
        "rev": "a6dca580a23b1c614f2e9d02c430250c0578d667",
        "sha256": "0qw3ls69wifwms7z14kmqxapr3r7j5zknn0dca8vpx3xvq2bhz3h",
        "type": "tarball",
        "url": "https://github.com/NixOS/nixpkgs/archive/a6dca580a23b1c614f2e9d02c430250c0578d667.tar.gz",
        "url_template": "https://github.com/<owner>/<repo>/archive/<rev>.tar.gz"
    },
    "yosys": {
        "branch": "master",
        "description": "Yosys Open SYnthesis Suite",
        "homepage": "http://www.clifford.at/yosys/",
        "owner": "cliffordwolf",
        "repo": "yosys",
        "rev": "7670a89e1fde7d0774695ab81031a90fafdf56b9",
        "sha256": "15d8gzw415ajp57kgkds3zvj88139q9rav4znaj0varw7m94kfsv",
        "type": "tarball",
        "url": "https://github.com/cliffordwolf/yosys/archive/7670a89e1fde7d0774695ab81031a90fafdf56b9.tar.gz",
        "url_template": "https://github.com/<owner>/<repo>/archive/<rev>.tar.gz"
    }
}
